kvq/KVQ.py
kvq/KVQConfig.py
kvq/__init__.py
kvq/bit_pattern.py
kvq/const.py
kvq-0.1.0.dist-info/licenses/LICENSE
kvq-0.1.0.dist-info/METADATA
kvq-0.1.0.dist-info/WHEEL
kvq-0.1.0.dist-info/top_level.txt
kvq-0.1.0.dist-info/RECORD
