Metadata-Version: 2.4
Name: kvq
Version: 0.1.0
Summary: Norm-Aware KVQuant: Precision Where It Counts
Author-email: Mohsen Hariri <mohsen.hariri@case.edu>
License: MIT
Project-URL: Homepage, https://mohsenhariri.github.io/kvq/
Project-URL: Repository, https://github.com/mohsenhariri/kvq
Project-URL: Issues, https://github.com/mohsenhariri/kvq/issues
Keywords: Large Language Models,Cache,Quantization,Compression,Optimization
Classifier: Programming Language :: Python :: 3.10
Classifier: License :: OSI Approved :: MIT License
Classifier: Operating System :: OS Independent
Requires-Python: >=3.10
License-File: LICENSE
Requires-Dist: transformers>=4.28.0
Requires-Dist: optimum-quanto>=0.2.7
Dynamic: license-file
